keisannkadai1.py
number_of_terms_inside_a_square_root8-0.0.6.dist-info/METADATA
number_of_terms_inside_a_square_root8-0.0.6.dist-info/WHEEL
number_of_terms_inside_a_square_root8-0.0.6.dist-info/entry_points.txt
number_of_terms_inside_a_square_root8-0.0.6.dist-info/top_level.txt
number_of_terms_inside_a_square_root8-0.0.6.dist-info/RECORD
