Metadata-Version: 2.1
Name: number-of-terms-inside-a-square-root8
Version: 0.0.6
Summary: Application to Determine the Number of Terms Inside a Square Root
Home-page: https://github.com/gomaW/suuzikadai4.git
Author: yuki shimizu
Author-email: s2222106@stu.musashino-u.ac.jp
Project-URL: Bug Tracker, https://github.com/gomaW/suuzikadai4/issues
Classifier: Programming Language :: Python :: 3
Classifier: License :: OSI Approved :: MIT License
Classifier: Operating System :: OS Independent
Requires-Python: >=3.8
